pystache/__init__.py
pystache/_version.py
pystache/common.py
pystache/context.py
pystache/defaults.py
pystache/init.py
pystache/loader.py
pystache/locator.py
pystache/parsed.py
pystache/parser.py
pystache/renderengine.py
pystache/renderer.py
pystache/specloader.py
pystache/template_spec.py
pystache/commands/__init__.py
pystache/commands/render.py
pystache/commands/test.py
pystache/tests/__init__.py
pystache/tests/benchmark.py
pystache/tests/common.py
pystache/tests/doctesting.py
pystache/tests/main.py
pystache/tests/spectesting.py
pystache/tests/test___init__.py
pystache/tests/test_commands.py
pystache/tests/test_context.py
pystache/tests/test_defaults.py
pystache/tests/test_examples.py
pystache/tests/test_loader.py
pystache/tests/test_locator.py
pystache/tests/test_parser.py
pystache/tests/test_pystache.py
pystache/tests/test_renderengine.py
pystache/tests/test_renderer.py
pystache/tests/test_simple.py
pystache/tests/test_specloader.py
pystache/tests/data/__init__.py
pystache/tests/data/ascii.mustache
pystache/tests/data/duplicate.mustache
pystache/tests/data/non_ascii.mustache
pystache/tests/data/sample_view.mustache
pystache/tests/data/say_hello.mustache
pystache/tests/data/views.py
pystache/tests/data/locator/__init__.py
pystache/tests/data/locator/duplicate.mustache
pystache/tests/data/locator/template.txt
pystache/tests/examples/__init__.py
pystache/tests/examples/comments.mustache
pystache/tests/examples/comments.py
pystache/tests/examples/complex.mustache
pystache/tests/examples/complex.py
pystache/tests/examples/delimiters.mustache
pystache/tests/examples/delimiters.py
pystache/tests/examples/double_section.mustache
pystache/tests/examples/double_section.py
pystache/tests/examples/escaped.mustache
pystache/tests/examples/escaped.py
pystache/tests/examples/extensionless
pystache/tests/examples/inner_partial.mustache
pystache/tests/examples/inner_partial.txt
pystache/tests/examples/inverted.mustache
pystache/tests/examples/inverted.py
pystache-0.6.7.dist-info/LICENSE
pystache-0.6.7.dist-info/METADATA
pystache-0.6.7.dist-info/WHEEL
pystache-0.6.7.dist-info/entry_points.txt
pystache-0.6.7.dist-info/top_level.txt
pystache-0.6.7.dist-info/RECORD
