Metadata-Version: 2.1
Name: pystache
Version: 0.6.7
Summary: Mustache for Python
Author-email: Chris Wanstrath <chris@ozmm.org>
Maintainer-email: Thomas David Baker <bakert@gmail.com>
License: Copyright (C) 2012 Chris Jerdonek.  All rights reserved.
Project-URL: Homepage, https://github.com/PennyDreadfulMTG/pystache
Project-URL: Documentation, http://mustache.github.io/
Project-URL: Repository, https://github.com/PennyDreadfulMTG/pystache.git
Project-URL: Changelog, https://github.com/PennyDreadfulMTG/pystache/blob/master/CHANGELOG.rst
Classifier: Development Status :: 4 - Beta
Classifier: Intended Audience :: Developers
Classifier: License :: OSI Approved :: MIT License
Classifier: Programming Language :: Python
Classifier: Programming Language :: Python :: 3 :: Only
Classifier: Programming Language :: Python :: 3.8
Classifier: Programming Language :: Python :: 3.9
Classifier: Programming Language :: Python :: 3.10
Classifier: Programming Language :: Python :: 3.11
Classifier: Programming Language :: Python :: 3.12
Classifier: Programming Language :: Python :: 3.13
Classifier: Topic :: Software Development :: Libraries
Requires-Python: >=3.8
License-File: LICENSE
Requires-Dist: importlib-metadata>=4.6; python_version < "3.10"
Provides-Extra: cov
Requires-Dist: coverage; extra == "cov"
Requires-Dist: coverage_python_version; extra == "cov"
Provides-Extra: doc
Requires-Dist: sphinx; extra == "doc"
Requires-Dist: sphinx_git; extra == "doc"
Requires-Dist: recommonmark; extra == "doc"
Requires-Dist: sphinx_rtd_theme; extra == "doc"
Requires-Dist: sphinxcontrib-apidoc; extra == "doc"
Provides-Extra: test
Requires-Dist: pytest; extra == "test"
Requires-Dist: pytest-cov; extra == "test"
